<?xml version="1.0" encoding="utf-8"?>
<VFScreenType xmlns:xsd="http://www.w3.org/2001/XMLSchema" xmlns:xsi="http://www.w3.org/2001/XMLSchema-instance">
  <screen_code>ENTITY-TYPE;OFFI,CON</screen_code>
  <description>Contact Details</description>
  <entry_order>S,2,1,3,4,5,6,7</entry_order>
  <index_fields>,</index_fields>
  <owner_type>ENTITY-TYPE;OFFI</owner_type>
  <view_script />
  <hide_script>S-CON-HIDE</hide_script>
  <text_screen>no</text_screen>
  <field_amend>0</field_amend>
  <view_authority>0</view_authority>
  <amend_authority>100</amend_authority>
  <boxes>3.38,1.6,126.4,15.48,15|^|1.2,1.8,81.2,5.4,15|^|6.8,1.8,81.2,5.4,15</boxes>
  <headers>Telephone,1.5,3.0,13.8,1.0,1,15,0,|^|Internet,7.1,3.0,9.2,1.0,1,15,0,</headers>
  <Fields>
    <field_info fld_number="1">
      <amend_authority>0</amend_authority>
      <description>Alternate</description>
      <default_value>""</default_value>
      <options>FONT,?,FGCOLOR,0,BGCOLOR,15,L-FONT,?,L-FGCOLOR,1,L-BGCOLOR,15,FCAT=,TRIMSPACES</options>
      <type>T</type>
      <selection_list />
      <row>3.91</row>
      <length>30</length>
      <column>21</column>
      <width>60</width>
      <pointer />
    </field_info>
    <field_info fld_number="2">
      <amend_authority>0</amend_authority>
      <description>Switchboard</description>
      <default_value>""</default_value>
      <options>FONT,?,FGCOLOR,0,BGCOLOR,15,L-FONT,?,L-FGCOLOR,1,L-BGCOLOR,15,FCAT=,TRIMSPACES</options>
      <type>T</type>
      <selection_list />
      <row>2.67</row>
      <length>30</length>
      <column>21</column>
      <width>60</width>
      <pointer />
    </field_info>
    <field_info fld_number="3">
      <amend_authority>0</amend_authority>
      <description>Fax</description>
      <default_value>""</default_value>
      <options>FONT,?,FGCOLOR,0,BGCOLOR,15,L-FONT,?,L-FGCOLOR,1,L-BGCOLOR,15,FCAT=,TRIMSPACES</options>
      <type>T</type>
      <selection_list />
      <row>5.14</row>
      <length>30</length>
      <column>21</column>
      <width>60</width>
      <pointer />
    </field_info>
    <field_info fld_number="4">
      <amend_authority>0</amend_authority>
      <description>Web Site</description>
      <default_value>""</default_value>
      <options>FONT,?,FGCOLOR,0,BGCOLOR,15,L-FONT,?,L-FGCOLOR,1,L-BGCOLOR,15,FCAT=,TRIMSPACES</options>
      <type>T</type>
      <selection_list />
      <row>8.29</row>
      <length>60</length>
      <column>21</column>
      <width>60</width>
      <pointer />
    </field_info>
    <field_info fld_number="5">
      <amend_authority>0</amend_authority>
      <description>Central Address</description>
      <default_value>""</default_value>
      <options>FONT,?,FGCOLOR,0,BGCOLOR,15,L-FONT,?,L-FGCOLOR,1,L-BGCOLOR,15,FCAT=,TRIMSPACES</options>
      <type>T</type>
      <selection_list />
      <row>9.52</row>
      <length>60</length>
      <column>21</column>
      <width>60</width>
      <pointer />
    </field_info>
    <field_info fld_number="6">
      <amend_authority>0</amend_authority>
      <description>Email</description>
      <default_value>""</default_value>
      <options>FONT,?,FGCOLOR,0,BGCOLOR,15,L-FONT,?,L-FGCOLOR,1,L-BGCOLOR,15,FCAT=,TRIMSPACES</options>
      <type>T</type>
      <selection_list />
      <row>10.76</row>
      <length>60</length>
      <column>21</column>
      <width>60</width>
      <pointer />
    </field_info>
    <field_info fld_number="7">
      <amend_authority />
      <description>@Point Off Name</description>
      <default_value />
      <options>FONT,?,FGCOLOR,0,BGCOLOR,15,L-FONT,?,L-FGCOLOR,1,L-BGCOLOR,15</options>
      <type>P</type>
      <selection_list />
      <row>1.43</row>
      <length>15</length>
      <column>21</column>
      <width>59.8</width>
      <pointer>OFF11,T,,</pointer>
    </field_info>
  </Fields>
</VFScreenType>